dantalabs/__init__.py
dantalabs/cli.py
dantalabs/cli/__init__.py
dantalabs/cli/app.py
dantalabs/cli/config.py
dantalabs/cli/commands/__init__.py
dantalabs/cli/commands/agentdb.py
dantalabs/cli/commands/agents.py
dantalabs/cli/commands/bundles.py
dantalabs/cli/commands/deploy.py
dantalabs/cli/commands/services.py
dantalabs/cli/commands/settings.py
dantalabs/cli/commands/setup.py
dantalabs/cli/commands/status.py
dantalabs/cli/commands/templates.py
dantalabs/cli/utils/__init__.py
dantalabs/cli/utils/client.py
dantalabs/cli/utils/deployment.py
dantalabs/cli/utils/github.py
dantalabs/cli/utils/schemas.py
dantalabs/maestro/__init__.py
dantalabs/maestro/client.py
dantalabs/maestro/exceptions.py
dantalabs/maestro/memory.py
dantalabs/maestro/models.py
dantalabs/maestro/bundles/__init__.py
dantalabs/maestro/bundles/creator.py
dantalabs/maestro/bundles/manager.py
dantalabs/maestro/http/__init__.py
dantalabs/maestro/http/base.py
dantalabs/maestro/resources/__init__.py
dantalabs/maestro/resources/agents.py
dantalabs/maestro/resources/executions.py
dantalabs/maestro/resources/files.py
dantalabs/maestro/resources/networks.py
dantalabs/maestro/resources/organizations.py
dantalabs-0.2.0.dist-info/licenses/LICENSE
dantalabs-0.2.0.dist-info/METADATA
dantalabs-0.2.0.dist-info/WHEEL
dantalabs-0.2.0.dist-info/entry_points.txt
dantalabs-0.2.0.dist-info/top_level.txt
dantalabs-0.2.0.dist-info/RECORD
